nebulagraph_lite-0.2.5.dist-info/METADATA
nebulagraph_lite-0.2.5.dist-info/WHEEL
nebulagraph_lite-0.2.5.dist-info/entry_points.txt
nebulagraph_lite-0.2.5.dist-info/licenses/LICENSE
nebulagraph_lite/__init__.py
nebulagraph_lite/cli.py
nebulagraph_lite/nebulagraph.py
nebulagraph_lite/utils.py
nebulagraph_lite-0.2.5.dist-info/RECORD
