Metadata-Version: 2.1
Name: nebulagraph-lite
Version: 0.2.5
Summary: Plug and play NebulaGraph with pip install.
Author-Email: Wey Gu <weyl.gu@gmail.com>
License: Apache 2.0
Requires-Python: >=3.8
Requires-Dist: udocker==1.3.13
Requires-Dist: psutil>=5.9.6
Requires-Dist: nebula3-python>=3.8.0
